Main/__init__.py
Main/logging_config.py
fdcLogger-0.3.dist-info/METADATA
fdcLogger-0.3.dist-info/WHEEL
fdcLogger-0.3.dist-info/top_level.txt
fdcLogger-0.3.dist-info/RECORD
