Metadata-Version: 2.1
Name: fdcLogger
Version: 0.3
Summary: Custom logging utility.
Author: Charles Fitzmaurice
Author-email: charles.fitzmaurice1993@gmail.com
